HISTORY.rst
LICENSE
MANIFEST.in
README.rst
flask_modus3.py
setup.py
Flask_Modus3.egg-info/PKG-INFO
Flask_Modus3.egg-info/SOURCES.txt
Flask_Modus3.egg-info/dependency_links.txt
Flask_Modus3.egg-info/not-zip-safe
Flask_Modus3.egg-info/requires.txt
Flask_Modus3.egg-info/top_level.txt