Metadata-Version: 1.1
Name: Flask-Modus3
Version: 0.0.4
Summary: Flask Method Overrides for python 2.7 and 3.6
Home-page: https://github.com/toChaim/flask-modus3
Author: Rhys Elsmore and Chaim Finkelman
Author-email: toChaim@gmail.com
License: Copyright 2013 Rhys Elsmore
